arcus_ml-1.0.11.1-py3.7-nspkg.pth
arcus/ml/__init__.py
arcus/ml/dataframes.py
arcus/ml/evaluation/__init__.py
arcus/ml/evaluation/classification.py
arcus/ml/images/__init__.py
arcus/ml/images/conversion.py
arcus/ml/images/explorer.py
arcus/ml/images/io.py
arcus/ml/neuralnetworks/__init__.py
arcus/ml/neuralnetworks/keras.py
arcus/ml/timeseries/__init__.py
arcus/ml/timeseries/timeops.py
arcus_ml-1.0.11.1.dist-info/LICENSE
arcus_ml-1.0.11.1.dist-info/METADATA
arcus_ml-1.0.11.1.dist-info/WHEEL
arcus_ml-1.0.11.1.dist-info/namespace_packages.txt
arcus_ml-1.0.11.1.dist-info/top_level.txt
arcus_ml-1.0.11.1.dist-info/RECORD
